Metadata-Version: 1.1
Name: django-xcache
Version: 0.1
Summary: Keeps backups of expired cached values.
Home-page: https://github.com/chadgh/django-xcache
Author: Chad G. Hansen
Author-email: chadgh@gmail.com
License: UNKNOWN
Platform: UNKNOWN
Classifier: Intended Audience :: Developers
Classifier: Operating System :: OS Independent
Classifier: Programming Language :: Python
Classifier: Programming Language :: Python :: 2.7
Classifier: Programming Language :: Python :: 3.4
Classifier: Programming Language :: Python :: 3.5
Classifier: Framework :: Django :: 1.8
Classifier: Framework :: Django :: 1.9
